titan_client/__init__.py
titan_client/api_client.py
titan_client/configuration.py
titan_client/exceptions.py
titan_client/rest.py
titan_client/api/__init__.py
titan_client/api/actors_api.py
titan_client/api/alerts_api.py
titan_client/api/credentials_api.py
titan_client/api/data_leak_blogs_api.py
titan_client/api/entities_api.py
titan_client/api/events_api.py
titan_client/api/forums_api.py
titan_client/api/girs_api.py
titan_client/api/global_search_api.py
titan_client/api/indicators_api.py
titan_client/api/iocs_api.py
titan_client/api/malware_families_api.py
titan_client/api/marketplaces_api.py
titan_client/api/messaging_services_api.py
titan_client/api/news_api.py
titan_client/api/reports_api.py
titan_client/api/tags_api.py
titan_client/api/vulnerabilities_api.py
titan_client/api/watchers_api.py
titan_client/api/yara_api.py
titan_client/models/__init__.py
titan_client/models/actors_get412_response.py
titan_client/models/alert_list_schema.py
titan_client/models/alert_list_schema_highlights_inner.py
titan_client/models/alert_list_schema_highlights_inner_chunks_inner.py
titan_client/models/alert_list_schema_report.py
titan_client/models/alert_list_schema_response.py
titan_client/models/alerts_get412_response.py
titan_client/models/breach_alerts_get412_response.py
titan_client/models/credential_accessed_url_schema.py
titan_client/models/credential_accessed_url_schema_activity.py
titan_client/models/credential_accessed_url_schema_classification.py
titan_client/models/credential_accessed_url_schema_data.py
titan_client/models/credential_accessed_url_schema_data_credential.py
titan_client/models/credential_accessed_url_stream_schema.py
titan_client/models/credential_accessed_urls_response.py
titan_client/models/credential_accessed_urls_stream_response.py
titan_client/models/credential_occurrence_schema.py
titan_client/models/credential_occurrence_schema_activity.py
titan_client/models/credential_occurrence_schema_classification.py
titan_client-1.20.0.15.dist-info/licenses/LICENSE
titan_client-1.20.0.15.dist-info/METADATA
titan_client-1.20.0.15.dist-info/WHEEL
titan_client-1.20.0.15.dist-info/top_level.txt
titan_client-1.20.0.15.dist-info/RECORD
