Metadata-Version: 2.4
Name: Titan-Client
Version: 1.20.0.15
Summary: Titan API v1
Home-page: https://github.com/intel471/titan-client-python
Author: Intel 471 Inc.
Author-email: support@intel471.com
License: MIT
Keywords: OpenAPI,OpenAPI-Generator,Titan API v1
Requires-Python: >=3.8
License-File: LICENSE
Requires-Dist: six>=1.10
Requires-Dist: python_dateutil>=2.5.3
Requires-Dist: setuptools>=21.0.0
Requires-Dist: urllib3>=2.2.1
Requires-Dist: stix2==3.0.1
Requires-Dist: PyYAML>=6.0.1
Requires-Dist: pycti>=6.3
Dynamic: author
Dynamic: author-email
Dynamic: description
Dynamic: description-content-type
Dynamic: home-page
Dynamic: keywords
Dynamic: license
Dynamic: license-file
Dynamic: requires-dist
Dynamic: requires-python
Dynamic: summary
